llamaplastics/__init__.py
llamaplastics/main_agent.py
llamaplastics/active_learning/__init__.py
llamaplastics/active_learning/acquisition.py
llamaplastics/active_learning/loop.py
llamaplastics/agent/__init__.py
llamaplastics/agent/agent.py
llamaplastics/agent/analyzer.py
llamaplastics/agent/executor.py
llamaplastics/agent/planner.py
llamaplastics/composition_encoding/__init__.py
llamaplastics/evaluation/__init__.py
llamaplastics/llm_interface/__init__.py
llamaplastics/llm_interface/embedder.py
llamaplastics/mlx_deployment/__init__.py
llamaplastics/optimization/__init__.py
llamaplastics/optimization/run_optimization.py
llamaplastics/property_predictor/__init__.py
llamaplastics/property_predictor/model.py
llamaplastics/robotics_interface/__init__.py
llamaplastics/robotics_interface/simulator_api.py
llamaplastics/simulation_interface/__init__.py
llamaplastics/training/__init__.py
llamaplastics_llamasearch-0.1.0.dist-info/licenses/LICENSE
research_plastics/__init__.py
llamaplastics_llamasearch-0.1.0.dist-info/METADATA
llamaplastics_llamasearch-0.1.0.dist-info/WHEEL
llamaplastics_llamasearch-0.1.0.dist-info/top_level.txt
llamaplastics_llamasearch-0.1.0.dist-info/RECORD
