Metadata-Version: 2.4
Name: llamaplastics-llamasearch
Version: 0.1.0
Summary: LlamaPlastics - A LlamaBench project
Author: LlamaSearch AI
Requires-Python: >=3.8
License-File: LICENSE
Dynamic: author
Dynamic: description
Dynamic: description-content-type
Dynamic: license-file
Dynamic: requires-python
Dynamic: summary
